{"nodes": [{"id": "c_techvelora_nexalink_src_services_realtimeservice_jsx", "label": "realtimeService.jsx", "file_type": "code", "source_file": "C:\\TechVelora_nexalink\\src\\services\\realtimeService.jsx", "source_location": "L1"}, {"id": "realtimeservice_getuser", "label": "getUser()", "file_type": "code", "source_file": "C:\\TechVelora_nexalink\\src\\services\\realtimeService.jsx", "source_location": "L6"}, {"id": "realtimeservice_getcompany", "label": "getCompany()", "file_type": "code", "source_file": "C:\\TechVelora_nexalink\\src\\services\\realtimeService.jsx", "source_location": "L11"}, {"id": "realtimeservice_updateuserprofile", "label": "updateUserProfile()", "file_type": "code", "source_file": "C:\\TechVelora_nexalink\\src\\services\\realtimeService.jsx", "source_location": "L16"}, {"id": "realtimeservice_createpost", "label": "createPost()", "file_type": "code", "source_file": "C:\\TechVelora_nexalink\\src\\services\\realtimeService.jsx", "source_location": "L23"}, {"id": "realtimeservice_getposts", "label": "getPosts()", "file_type": "code", "source_file": "C:\\TechVelora_nexalink\\src\\services\\realtimeService.jsx", "source_location": "L48"}, {"id": "realtimeservice_recalculatetrustscore", "label": "recalculateTrustScore()", "file_type": "code", "source_file": "C:\\TechVelora_nexalink\\src\\services\\realtimeService.jsx", "source_location": "L109"}, {"id": "realtimeservice_getjobs", "label": "getJobs()", "file_type": "code", "source_file": "C:\\TechVelora_nexalink\\src\\services\\realtimeService.jsx", "source_location": "L120"}, {"id": "realtimeservice_createjob", "label": "createJob()", "file_type": "code", "source_file": "C:\\TechVelora_nexalink\\src\\services\\realtimeService.jsx", "source_location": "L131"}, {"id": "realtimeservice_getevents", "label": "getEvents()", "file_type": "code", "source_file": "C:\\TechVelora_nexalink\\src\\services\\realtimeService.jsx", "source_location": "L139"}, {"id": "realtimeservice_getconnections", "label": "getConnections()", "file_type": "code", "source_file": "C:\\TechVelora_nexalink\\src\\services\\realtimeService.jsx", "source_location": "L152"}, {"id": "realtimeservice_getallusers", "label": "getAllUsers()", "file_type": "code", "source_file": "C:\\TechVelora_nexalink\\src\\services\\realtimeService.jsx", "source_location": "L164"}, {"id": "realtimeservice_getpendingrequests", "label": "getPendingRequests()", "file_type": "code", "source_file": "C:\\TechVelora_nexalink\\src\\services\\realtimeService.jsx", "source_location": "L175"}, {"id": "realtimeservice_sendconnectionrequest", "label": "sendConnectionRequest()", "file_type": "code", "source_file": "C:\\TechVelora_nexalink\\src\\services\\realtimeService.jsx", "source_location": "L187"}, {"id": "realtimeservice_acceptconnection", "label": "acceptConnection()", "file_type": "code", "source_file": "C:\\TechVelora_nexalink\\src\\services\\realtimeService.jsx", "source_location": "L209"}, {"id": "realtimeservice_rejectconnection", "label": "rejectConnection()", "file_type": "code", "source_file": "C:\\TechVelora_nexalink\\src\\services\\realtimeService.jsx", "source_location": "L233"}, {"id": "realtimeservice_createevent", "label": "createEvent()", "file_type": "code", "source_file": "C:\\TechVelora_nexalink\\src\\services\\realtimeService.jsx", "source_location": "L239"}, {"id": "realtimeservice_registerforevent", "label": "registerForEvent()", "file_type": "code", "source_file": "C:\\TechVelora_nexalink\\src\\services\\realtimeService.jsx", "source_location": "L245"}, {"id": "realtimeservice_likepost", "label": "likePost()", "file_type": "code", "source_file": "C:\\TechVelora_nexalink\\src\\services\\realtimeService.jsx", "source_location": "L258"}, {"id": "realtimeservice_addcomment", "label": "addComment()", "file_type": "code", "source_file": "C:\\TechVelora_nexalink\\src\\services\\realtimeService.jsx", "source_location": "L279"}, {"id": "realtimeservice_getcomments", "label": "getComments()", "file_type": "code", "source_file": "C:\\TechVelora_nexalink\\src\\services\\realtimeService.jsx", "source_location": "L293"}], "edges": [{"source": "c_techvelora_nexalink_src_services_realtimeservice_jsx", "target": "database", "relation": "imports_from", "confidence": "EXTRACTED", "source_file": "C:\\TechVelora_nexalink\\src\\services\\realtimeService.jsx", "source_location": "L1", "weight": 1.0}, {"source": "c_techvelora_nexalink_src_services_realtimeservice_jsx", "target": "c_techvelora_nexalink_src_config_firebase", "relation": "imports_from", "confidence": "EXTRACTED", "source_file": "C:\\TechVelora_nexalink\\src\\services\\realtimeService.jsx", "source_location": "L2", "weight": 1.0}, {"source": "c_techvelora_nexalink_src_services_realtimeservice_jsx", "target": "realtimeservice_getuser", "relation": "contains", "confidence": "EXTRACTED", "source_file": "C:\\TechVelora_nexalink\\src\\services\\realtimeService.jsx", "source_location": "L6", "weight": 1.0}, {"source": "c_techvelora_nexalink_src_services_realtimeservice_jsx", "target": "realtimeservice_getcompany", "relation": "contains", "confidence": "EXTRACTED", "source_file": "C:\\TechVelora_nexalink\\src\\services\\realtimeService.jsx", "source_location": "L11", "weight": 1.0}, {"source": "c_techvelora_nexalink_src_services_realtimeservice_jsx", "target": "realtimeservice_updateuserprofile", "relation": "contains", "confidence": "EXTRACTED", "source_file": "C:\\TechVelora_nexalink\\src\\services\\realtimeService.jsx", "source_location": "L16", "weight": 1.0}, {"source": "c_techvelora_nexalink_src_services_realtimeservice_jsx", "target": "realtimeservice_createpost", "relation": "contains", "confidence": "EXTRACTED", "source_file": "C:\\TechVelora_nexalink\\src\\services\\realtimeService.jsx", "source_location": "L23", "weight": 1.0}, {"source": "c_techvelora_nexalink_src_services_realtimeservice_jsx", "target": "realtimeservice_getposts", "relation": "contains", "confidence": "EXTRACTED", "source_file": "C:\\TechVelora_nexalink\\src\\services\\realtimeService.jsx", "source_location": "L48", "weight": 1.0}, {"source": "c_techvelora_nexalink_src_services_realtimeservice_jsx", "target": "realtimeservice_recalculatetrustscore", "relation": "contains", "confidence": "EXTRACTED", "source_file": "C:\\TechVelora_nexalink\\src\\services\\realtimeService.jsx", "source_location": "L109", "weight": 1.0}, {"source": "c_techvelora_nexalink_src_services_realtimeservice_jsx", "target": "realtimeservice_getjobs", "relation": "contains", "confidence": "EXTRACTED", "source_file": "C:\\TechVelora_nexalink\\src\\services\\realtimeService.jsx", "source_location": "L120", "weight": 1.0}, {"source": "c_techvelora_nexalink_src_services_realtimeservice_jsx", "target": "realtimeservice_createjob", "relation": "contains", "confidence": "EXTRACTED", "source_file": "C:\\TechVelora_nexalink\\src\\services\\realtimeService.jsx", "source_location": "L131", "weight": 1.0}, {"source": "c_techvelora_nexalink_src_services_realtimeservice_jsx", "target": "realtimeservice_getevents", "relation": "contains", "confidence": "EXTRACTED", "source_file": "C:\\TechVelora_nexalink\\src\\services\\realtimeService.jsx", "source_location": "L139", "weight": 1.0}, {"source": "c_techvelora_nexalink_src_services_realtimeservice_jsx", "target": "realtimeservice_getconnections", "relation": "contains", "confidence": "EXTRACTED", "source_file": "C:\\TechVelora_nexalink\\src\\services\\realtimeService.jsx", "source_location": "L152", "weight": 1.0}, {"source": "c_techvelora_nexalink_src_services_realtimeservice_jsx", "target": "realtimeservice_getallusers", "relation": "contains", "confidence": "EXTRACTED", "source_file": "C:\\TechVelora_nexalink\\src\\services\\realtimeService.jsx", "source_location": "L164", "weight": 1.0}, {"source": "c_techvelora_nexalink_src_services_realtimeservice_jsx", "target": "realtimeservice_getpendingrequests", "relation": "contains", "confidence": "EXTRACTED", "source_file": "C:\\TechVelora_nexalink\\src\\services\\realtimeService.jsx", "source_location": "L175", "weight": 1.0}, {"source": "c_techvelora_nexalink_src_services_realtimeservice_jsx", "target": "realtimeservice_sendconnectionrequest", "relation": "contains", "confidence": "EXTRACTED", "source_file": "C:\\TechVelora_nexalink\\src\\services\\realtimeService.jsx", "source_location": "L187", "weight": 1.0}, {"source": "c_techvelora_nexalink_src_services_realtimeservice_jsx", "target": "realtimeservice_acceptconnection", "relation": "contains", "confidence": "EXTRACTED", "source_file": "C:\\TechVelora_nexalink\\src\\services\\realtimeService.jsx", "source_location": "L209", "weight": 1.0}, {"source": "c_techvelora_nexalink_src_services_realtimeservice_jsx", "target": "realtimeservice_rejectconnection", "relation": "contains", "confidence": "EXTRACTED", "source_file": "C:\\TechVelora_nexalink\\src\\services\\realtimeService.jsx", "source_location": "L233", "weight": 1.0}, {"source": "c_techvelora_nexalink_src_services_realtimeservice_jsx", "target": "realtimeservice_createevent", "relation": "contains", "confidence": "EXTRACTED", "source_file": "C:\\TechVelora_nexalink\\src\\services\\realtimeService.jsx", "source_location": "L239", "weight": 1.0}, {"source": "c_techvelora_nexalink_src_services_realtimeservice_jsx", "target": "realtimeservice_registerforevent", "relation": "contains", "confidence": "EXTRACTED", "source_file": "C:\\TechVelora_nexalink\\src\\services\\realtimeService.jsx", "source_location": "L245", "weight": 1.0}, {"source": "c_techvelora_nexalink_src_services_realtimeservice_jsx", "target": "realtimeservice_likepost", "relation": "contains", "confidence": "EXTRACTED", "source_file": "C:\\TechVelora_nexalink\\src\\services\\realtimeService.jsx", "source_location": "L258", "weight": 1.0}, {"source": "c_techvelora_nexalink_src_services_realtimeservice_jsx", "target": "realtimeservice_addcomment", "relation": "contains", "confidence": "EXTRACTED", "source_file": "C:\\TechVelora_nexalink\\src\\services\\realtimeService.jsx", "source_location": "L279", "weight": 1.0}, {"source": "c_techvelora_nexalink_src_services_realtimeservice_jsx", "target": "realtimeservice_getcomments", "relation": "contains", "confidence": "EXTRACTED", "source_file": "C:\\TechVelora_nexalink\\src\\services\\realtimeService.jsx", "source_location": "L293", "weight": 1.0}, {"source": "realtimeservice_getconnections", "target": "realtimeservice_getuser", "relation": "calls", "confidence": "EXTRACTED", "source_file": "C:\\TechVelora_nexalink\\src\\services\\realtimeService.jsx", "source_location": "L157", "weight": 1.0}, {"source": "realtimeservice_getpendingrequests", "target": "realtimeservice_getuser", "relation": "calls", "confidence": "EXTRACTED", "source_file": "C:\\TechVelora_nexalink\\src\\services\\realtimeService.jsx", "source_location": "L180", "weight": 1.0}], "raw_calls": [{"caller_nid": "realtimeservice_getuser", "callee": "get", "source_file": "C:\\TechVelora_nexalink\\src\\services\\realtimeService.jsx", "source_location": "L7"}, {"caller_nid": "realtimeservice_getuser", "callee": "ref", "source_file": "C:\\TechVelora_nexalink\\src\\services\\realtimeService.jsx", "source_location": "L7"}, {"caller_nid": "realtimeservice_getuser", "callee": "exists", "source_file": "C:\\TechVelora_nexalink\\src\\services\\realtimeService.jsx", "source_location": "L8"}, {"caller_nid": "realtimeservice_getuser", "callee": "val", "source_file": "C:\\TechVelora_nexalink\\src\\services\\realtimeService.jsx", "source_location": "L8"}, {"caller_nid": "realtimeservice_getcompany", "callee": "get", "source_file": "C:\\TechVelora_nexalink\\src\\services\\realtimeService.jsx", "source_location": "L12"}, {"caller_nid": "realtimeservice_getcompany", "callee": "ref", "source_file": "C:\\TechVelora_nexalink\\src\\services\\realtimeService.jsx", "source_location": "L12"}, {"caller_nid": "realtimeservice_getcompany", "callee": "exists", "source_file": "C:\\TechVelora_nexalink\\src\\services\\realtimeService.jsx", "source_location": "L13"}, {"caller_nid": "realtimeservice_getcompany", "callee": "val", "source_file": "C:\\TechVelora_nexalink\\src\\services\\realtimeService.jsx", "source_location": "L13"}, {"caller_nid": "realtimeservice_updateuserprofile", "callee": "update", "source_file": "C:\\TechVelora_nexalink\\src\\services\\realtimeService.jsx", "source_location": "L18"}, {"caller_nid": "realtimeservice_updateuserprofile", "callee": "ref", "source_file": "C:\\TechVelora_nexalink\\src\\services\\realtimeService.jsx", "source_location": "L18"}, {"caller_nid": "realtimeservice_updateuserprofile", "callee": "serverTimestamp", "source_file": "C:\\TechVelora_nexalink\\src\\services\\realtimeService.jsx", "source_location": "L18"}, {"caller_nid": "realtimeservice_createpost", "callee": "push", "source_file": "C:\\TechVelora_nexalink\\src\\services\\realtimeService.jsx", "source_location": "L25"}, {"caller_nid": "realtimeservice_createpost", "callee": "ref", "source_file": "C:\\TechVelora_nexalink\\src\\services\\realtimeService.jsx", "source_location": "L25"}, {"caller_nid": "realtimeservice_createpost", "callee": "set", "source_file": "C:\\TechVelora_nexalink\\src\\services\\realtimeService.jsx", "source_location": "L28"}, {"caller_nid": "realtimeservice_createpost", "callee": "now", "source_file": "C:\\TechVelora_nexalink\\src\\services\\realtimeService.jsx", "source_location": "L33"}, {"caller_nid": "realtimeservice_createpost", "callee": "ref", "source_file": "C:\\TechVelora_nexalink\\src\\services\\realtimeService.jsx", "source_location": "L38"}, {"caller_nid": "realtimeservice_createpost", "callee": "get", "source_file": "C:\\TechVelora_nexalink\\src\\services\\realtimeService.jsx", "source_location": "L39"}, {"caller_nid": "realtimeservice_createpost", "callee": "exists", "source_file": "C:\\TechVelora_nexalink\\src\\services\\realtimeService.jsx", "source_location": "L40"}, {"caller_nid": "realtimeservice_createpost", "callee": "val", "source_file": "C:\\TechVelora_nexalink\\src\\services\\realtimeService.jsx", "source_location": "L41"}, {"caller_nid": "realtimeservice_createpost", "callee": "update", "source_file": "C:\\TechVelora_nexalink\\src\\services\\realtimeService.jsx", "source_location": "L42"}, {"caller_nid": "realtimeservice_getposts", "callee": "fetch", "source_file": "C:\\TechVelora_nexalink\\src\\services\\realtimeService.jsx", "source_location": "L52"}, {"caller_nid": "realtimeservice_getposts", "callee": "json", "source_file": "C:\\TechVelora_nexalink\\src\\services\\realtimeService.jsx", "source_location": "L54"}, {"caller_nid": "realtimeservice_getposts", "callee": "warn", "source_file": "C:\\TechVelora_nexalink\\src\\services\\realtimeService.jsx", "source_location": "L58"}, {"caller_nid": "realtimeservice_getposts", "callee": "get", "source_file": "C:\\TechVelora_nexalink\\src\\services\\realtimeService.jsx", "source_location": "L64"}, {"caller_nid": "realtimeservice_getposts", "callee": "ref", "source_file": "C:\\TechVelora_nexalink\\src\\services\\realtimeService.jsx", "source_location": "L64"}, {"caller_nid": "realtimeservice_getposts", "callee": "exists", "source_file": "C:\\TechVelora_nexalink\\src\\services\\realtimeService.jsx", "source_location": "L65"}, {"caller_nid": "realtimeservice_getposts", "callee": "push", "source_file": "C:\\TechVelora_nexalink\\src\\services\\realtimeService.jsx", "source_location": "L66"}, {"caller_nid": "realtimeservice_getposts", "callee": "keys", "source_file": "C:\\TechVelora_nexalink\\src\\services\\realtimeService.jsx", "source_location": "L66"}, {"caller_nid": "realtimeservice_getposts", "callee": "val", "source_file": "C:\\TechVelora_nexalink\\src\\services\\realtimeService.jsx", "source_location": "L66"}, {"caller_nid": "realtimeservice_getposts", "callee": "get", "source_file": "C:\\TechVelora_nexalink\\src\\services\\realtimeService.jsx", "source_location": "L71"}, {"caller_nid": "realtimeservice_getposts", "callee": "ref", "source_file": "C:\\TechVelora_nexalink\\src\\services\\realtimeService.jsx", "source_location": "L71"}, {"caller_nid": "realtimeservice_getposts", "callee": "exists", "source_file": "C:\\TechVelora_nexalink\\src\\services\\realtimeService.jsx", "source_location": "L73"}, {"caller_nid": "realtimeservice_getposts", "callee": "val", "source_file": "C:\\TechVelora_nexalink\\src\\services\\realtimeService.jsx", "source_location": "L74"}, {"caller_nid": "realtimeservice_getposts", "callee": "keys", "source_file": "C:\\TechVelora_nexalink\\src\\services\\realtimeService.jsx", "source_location": "L76"}, {"caller_nid": "realtimeservice_getposts", "callee": "includes", "source_file": "C:\\TechVelora_nexalink\\src\\services\\realtimeService.jsx", "source_location": "L82"}, {"caller_nid": "realtimeservice_getposts", "callee": "push", "source_file": "C:\\TechVelora_nexalink\\src\\services\\realtimeService.jsx", "source_location": "L83"}, {"caller_nid": "realtimeservice_getposts", "callee": "includes", "source_file": "C:\\TechVelora_nexalink\\src\\services\\realtimeService.jsx", "source_location": "L88"}, {"caller_nid": "realtimeservice_getposts", "callee": "entries", "source_file": "C:\\TechVelora_nexalink\\src\\services\\realtimeService.jsx", "source_location": "L92"}, {"caller_nid": "realtimeservice_getposts", "callee": "push", "source_file": "C:\\TechVelora_nexalink\\src\\services\\realtimeService.jsx", "source_location": "L93"}, {"caller_nid": "realtimeservice_getposts", "callee": "sort", "source_file": "C:\\TechVelora_nexalink\\src\\services\\realtimeService.jsx", "source_location": "L100"}, {"caller_nid": "realtimeservice_getposts", "callee": "slice", "source_file": "C:\\TechVelora_nexalink\\src\\services\\realtimeService.jsx", "source_location": "L103"}, {"caller_nid": "realtimeservice_recalculatetrustscore", "callee": "fetch", "source_file": "C:\\TechVelora_nexalink\\src\\services\\realtimeService.jsx", "source_location": "L111"}, {"caller_nid": "realtimeservice_recalculatetrustscore", "callee": "json", "source_file": "C:\\TechVelora_nexalink\\src\\services\\realtimeService.jsx", "source_location": "L112"}, {"caller_nid": "realtimeservice_recalculatetrustscore", "callee": "error", "source_file": "C:\\TechVelora_nexalink\\src\\services\\realtimeService.jsx", "source_location": "L114"}, {"caller_nid": "realtimeservice_getjobs", "callee": "get", "source_file": "C:\\TechVelora_nexalink\\src\\services\\realtimeService.jsx", "source_location": "L121"}, {"caller_nid": "realtimeservice_getjobs", "callee": "ref", "source_file": "C:\\TechVelora_nexalink\\src\\services\\realtimeService.jsx", "source_location": "L121"}, {"caller_nid": "realtimeservice_getjobs", "callee": "exists", "source_file": "C:\\TechVelora_nexalink\\src\\services\\realtimeService.jsx", "source_location": "L123"}, {"caller_nid": "realtimeservice_getjobs", "callee": "forEach", "source_file": "C:\\TechVelora_nexalink\\src\\services\\realtimeService.jsx", "source_location": "L124"}, {"caller_nid": "realtimeservice_getjobs", "callee": "reverse", "source_file": "C:\\TechVelora_nexalink\\src\\services\\realtimeService.jsx", "source_location": "L128"}, {"caller_nid": "realtimeservice_createjob", "callee": "push", "source_file": "C:\\TechVelora_nexalink\\src\\services\\realtimeService.jsx", "source_location": "L132"}, {"caller_nid": "realtimeservice_createjob", "callee": "ref", "source_file": "C:\\TechVelora_nexalink\\src\\services\\realtimeService.jsx", "source_location": "L132"}, {"caller_nid": "realtimeservice_createjob", "callee": "set", "source_file": "C:\\TechVelora_nexalink\\src\\services\\realtimeService.jsx", "source_location": "L133"}, {"caller_nid": "realtimeservice_createjob", "callee": "now", "source_file": "C:\\TechVelora_nexalink\\src\\services\\realtimeService.jsx", "source_location": "L133"}, {"caller_nid": "realtimeservice_getevents", "callee": "get", "source_file": "C:\\TechVelora_nexalink\\src\\services\\realtimeService.jsx", "source_location": "L140"}, {"caller_nid": "realtimeservice_getevents", "callee": "ref", "source_file": "C:\\TechVelora_nexalink\\src\\services\\realtimeService.jsx", "source_location": "L140"}, {"caller_nid": "realtimeservice_getevents", "callee": "exists", "source_file": "C:\\TechVelora_nexalink\\src\\services\\realtimeService.jsx", "source_location": "L142"}, {"caller_nid": "realtimeservice_getevents", "callee": "forEach", "source_file": "C:\\TechVelora_nexalink\\src\\services\\realtimeService.jsx", "source_location": "L143"}, {"caller_nid": "realtimeservice_getevents", "callee": "reverse", "source_file": "C:\\TechVelora_nexalink\\src\\services\\realtimeService.jsx", "source_location": "L147"}, {"caller_nid": "realtimeservice_getconnections", "callee": "get", "source_file": "C:\\TechVelora_nexalink\\src\\services\\realtimeService.jsx", "source_location": "L153"}, {"caller_nid": "realtimeservice_getconnections", "callee": "ref", "source_file": "C:\\TechVelora_nexalink\\src\\services\\realtimeService.jsx", "source_location": "L153"}, {"caller_nid": "realtimeservice_getconnections", "callee": "exists", "source_file": "C:\\TechVelora_nexalink\\src\\services\\realtimeService.jsx", "source_location": "L155"}, {"caller_nid": "realtimeservice_getconnections", "callee": "keys", "source_file": "C:\\TechVelora_nexalink\\src\\services\\realtimeService.jsx", "source_location": "L156"}, {"caller_nid": "realtimeservice_getconnections", "callee": "val", "source_file": "C:\\TechVelora_nexalink\\src\\services\\realtimeService.jsx", "source_location": "L156"}, {"caller_nid": "realtimeservice_getconnections", "callee": "push", "source_file": "C:\\TechVelora_nexalink\\src\\services\\realtimeService.jsx", "source_location": "L158"}, {"caller_nid": "realtimeservice_getallusers", "callee": "get", "source_file": "C:\\TechVelora_nexalink\\src\\services\\realtimeService.jsx", "source_location": "L165"}, {"caller_nid": "realtimeservice_getallusers", "callee": "query", "source_file": "C:\\TechVelora_nexalink\\src\\services\\realtimeService.jsx", "source_location": "L165"}, {"caller_nid": "realtimeservice_getallusers", "callee": "ref", "source_file": "C:\\TechVelora_nexalink\\src\\services\\realtimeService.jsx", "source_location": "L165"}, {"caller_nid": "realtimeservice_getallusers", "callee": "limitToLast", "source_file": "C:\\TechVelora_nexalink\\src\\services\\realtimeService.jsx", "source_location": "L165"}, {"caller_nid": "realtimeservice_getallusers", "callee": "exists", "source_file": "C:\\TechVelora_nexalink\\src\\services\\realtimeService.jsx", "source_location": "L167"}, {"caller_nid": "realtimeservice_getallusers", "callee": "forEach", "source_file": "C:\\TechVelora_nexalink\\src\\services\\realtimeService.jsx", "source_location": "L168"}, {"caller_nid": "realtimeservice_getallusers", "callee": "reverse", "source_file": "C:\\TechVelora_nexalink\\src\\services\\realtimeService.jsx", "source_location": "L172"}, {"caller_nid": "realtimeservice_getpendingrequests", "callee": "get", "source_file": "C:\\TechVelora_nexalink\\src\\services\\realtimeService.jsx", "source_location": "L176"}, {"caller_nid": "realtimeservice_getpendingrequests", "callee": "ref", "source_file": "C:\\TechVelora_nexalink\\src\\services\\realtimeService.jsx", "source_location": "L176"}, {"caller_nid": "realtimeservice_getpendingrequests", "callee": "exists", "source_file": "C:\\TechVelora_nexalink\\src\\services\\realtimeService.jsx", "source_location": "L178"}, {"caller_nid": "realtimeservice_getpendingrequests", "callee": "entries", "source_file": "C:\\TechVelora_nexalink\\src\\services\\realtimeService.jsx", "source_location": "L179"}, {"caller_nid": "realtimeservice_getpendingrequests", "callee": "val", "source_file": "C:\\TechVelora_nexalink\\src\\services\\realtimeService.jsx", "source_location": "L179"}, {"caller_nid": "realtimeservice_getpendingrequests", "callee": "push", "source_file": "C:\\TechVelora_nexalink\\src\\services\\realtimeService.jsx", "source_location": "L181"}, {"caller_nid": "realtimeservice_sendconnectionrequest", "callee": "get", "source_file": "C:\\TechVelora_nexalink\\src\\services\\realtimeService.jsx", "source_location": "L191"}, {"caller_nid": "realtimeservice_sendconnectionrequest", "callee": "ref", "source_file": "C:\\TechVelora_nexalink\\src\\services\\realtimeService.jsx", "source_location": "L191"}, {"caller_nid": "realtimeservice_sendconnectionrequest", "callee": "exists", "source_file": "C:\\TechVelora_nexalink\\src\\services\\realtimeService.jsx", "source_location": "L192"}, {"caller_nid": "realtimeservice_sendconnectionrequest", "callee": "get", "source_file": "C:\\TechVelora_nexalink\\src\\services\\realtimeService.jsx", "source_location": "L194"}, {"caller_nid": "realtimeservice_sendconnectionrequest", "callee": "ref", "source_file": "C:\\TechVelora_nexalink\\src\\services\\realtimeService.jsx", "source_location": "L194"}, {"caller_nid": "realtimeservice_sendconnectionrequest", "callee": "exists", "source_file": "C:\\TechVelora_nexalink\\src\\services\\realtimeService.jsx", "source_location": "L195"}, {"caller_nid": "realtimeservice_sendconnectionrequest", "callee": "get", "source_file": "C:\\TechVelora_nexalink\\src\\services\\realtimeService.jsx", "source_location": "L197"}, {"caller_nid": "realtimeservice_sendconnectionrequest", "callee": "ref", "source_file": "C:\\TechVelora_nexalink\\src\\services\\realtimeService.jsx", "source_location": "L197"}, {"caller_nid": "realtimeservice_sendconnectionrequest", "callee": "exists", "source_file": "C:\\TechVelora_nexalink\\src\\services\\realtimeService.jsx", "source_location": "L198"}, {"caller_nid": "realtimeservice_sendconnectionrequest", "callee": "ref", "source_file": "C:\\TechVelora_nexalink\\src\\services\\realtimeService.jsx", "source_location": "L200"}, {"caller_nid": "realtimeservice_sendconnectionrequest", "callee": "set", "source_file": "C:\\TechVelora_nexalink\\src\\services\\realtimeService.jsx", "source_location": "L201"}, {"caller_nid": "realtimeservice_sendconnectionrequest", "callee": "now", "source_file": "C:\\TechVelora_nexalink\\src\\services\\realtimeService.jsx", "source_location": "L204"}, {"caller_nid": "realtimeservice_acceptconnection", "callee": "set", "source_file": "C:\\TechVelora_nexalink\\src\\services\\realtimeService.jsx", "source_location": "L211"}, {"caller_nid": "realtimeservice_acceptconnection", "callee": "ref", "source_file": "C:\\TechVelora_nexalink\\src\\services\\realtimeService.jsx", "source_location": "L211"}, {"caller_nid": "realtimeservice_acceptconnection", "callee": "now", "source_file": "C:\\TechVelora_nexalink\\src\\services\\realtimeService.jsx", "source_location": "L211"}, {"caller_nid": "realtimeservice_acceptconnection", "callee": "set", "source_file": "C:\\TechVelora_nexalink\\src\\services\\realtimeService.jsx", "source_location": "L212"}, {"caller_nid": "realtimeservice_acceptconnection", "callee": "ref", "source_file": "C:\\TechVelora_nexalink\\src\\services\\realtimeService.jsx", "source_location": "L212"}, {"caller_nid": "realtimeservice_acceptconnection", "callee": "now", "source_file": "C:\\TechVelora_nexalink\\src\\services\\realtimeService.jsx", "source_location": "L212"}, {"caller_nid": "realtimeservice_acceptconnection", "callee": "ref", "source_file": "C:\\TechVelora_nexalink\\src\\services\\realtimeService.jsx", "source_location": "L216"}, {"caller_nid": "realtimeservice_acceptconnection", "callee": "get", "source_file": "C:\\TechVelora_nexalink\\src\\services\\realtimeService.jsx", "source_location": "L217"}, {"caller_nid": "realtimeservice_acceptconnection", "callee": "exists", "source_file": "C:\\TechVelora_nexalink\\src\\services\\realtimeService.jsx", "source_location": "L219"}, {"caller_nid": "realtimeservice_acceptconnection", "callee": "ref", "source_file": "C:\\TechVelora_nexalink\\src\\services\\realtimeService.jsx", "source_location": "L220"}, {"caller_nid": "realtimeservice_acceptconnection", "callee": "get", "source_file": "C:\\TechVelora_nexalink\\src\\services\\realtimeService.jsx", "source_location": "L221"}, {"caller_nid": "realtimeservice_acceptconnection", "callee": "exists", "source_file": "C:\\TechVelora_nexalink\\src\\services\\realtimeService.jsx", "source_location": "L224"}, {"caller_nid": "realtimeservice_acceptconnection", "callee": "update", "source_file": "C:\\TechVelora_nexalink\\src\\services\\realtimeService.jsx", "source_location": "L225"}, {"caller_nid": "realtimeservice_acceptconnection", "callee": "val", "source_file": "C:\\TechVelora_nexalink\\src\\services\\realtimeService.jsx", "source_location": "L225"}, {"caller_nid": "realtimeservice_acceptconnection", "callee": "remove", "source_file": "C:\\TechVelora_nexalink\\src\\services\\realtimeService.jsx", "source_location": "L230"}, {"caller_nid": "realtimeservice_acceptconnection", "callee": "ref", "source_file": "C:\\TechVelora_nexalink\\src\\services\\realtimeService.jsx", "source_location": "L230"}, {"caller_nid": "realtimeservice_rejectconnection", "callee": "remove", "source_file": "C:\\TechVelora_nexalink\\src\\services\\realtimeService.jsx", "source_location": "L235"}, {"caller_nid": "realtimeservice_rejectconnection", "callee": "ref", "source_file": "C:\\TechVelora_nexalink\\src\\services\\realtimeService.jsx", "source_location": "L235"}, {"caller_nid": "realtimeservice_createevent", "callee": "push", "source_file": "C:\\TechVelora_nexalink\\src\\services\\realtimeService.jsx", "source_location": "L240"}, {"caller_nid": "realtimeservice_createevent", "callee": "ref", "source_file": "C:\\TechVelora_nexalink\\src\\services\\realtimeService.jsx", "source_location": "L240"}, {"caller_nid": "realtimeservice_createevent", "callee": "set", "source_file": "C:\\TechVelora_nexalink\\src\\services\\realtimeService.jsx", "source_location": "L241"}, {"caller_nid": "realtimeservice_createevent", "callee": "now", "source_file": "C:\\TechVelora_nexalink\\src\\services\\realtimeService.jsx", "source_location": "L241"}, {"caller_nid": "realtimeservice_registerforevent", "callee": "ref", "source_file": "C:\\TechVelora_nexalink\\src\\services\\realtimeService.jsx", "source_location": "L246"}, {"caller_nid": "realtimeservice_registerforevent", "callee": "set", "source_file": "C:\\TechVelora_nexalink\\src\\services\\realtimeService.jsx", "source_location": "L247"}, {"caller_nid": "realtimeservice_registerforevent", "callee": "now", "source_file": "C:\\TechVelora_nexalink\\src\\services\\realtimeService.jsx", "source_location": "L247"}, {"caller_nid": "realtimeservice_registerforevent", "callee": "ref", "source_file": "C:\\TechVelora_nexalink\\src\\services\\realtimeService.jsx", "source_location": "L250"}, {"caller_nid": "realtimeservice_registerforevent", "callee": "get", "source_file": "C:\\TechVelora_nexalink\\src\\services\\realtimeService.jsx", "source_location": "L251"}, {"caller_nid": "realtimeservice_registerforevent", "callee": "exists", "source_file": "C:\\TechVelora_nexalink\\src\\services\\realtimeService.jsx", "source_location": "L252"}, {"caller_nid": "realtimeservice_registerforevent", "callee": "update", "source_file": "C:\\TechVelora_nexalink\\src\\services\\realtimeService.jsx", "source_location": "L253"}, {"caller_nid": "realtimeservice_registerforevent", "callee": "val", "source_file": "C:\\TechVelora_nexalink\\src\\services\\realtimeService.jsx", "source_location": "L253"}, {"caller_nid": "realtimeservice_likepost", "callee": "ref", "source_file": "C:\\TechVelora_nexalink\\src\\services\\realtimeService.jsx", "source_location": "L260"}, {"caller_nid": "realtimeservice_likepost", "callee": "ref", "source_file": "C:\\TechVelora_nexalink\\src\\services\\realtimeService.jsx", "source_location": "L261"}, {"caller_nid": "realtimeservice_likepost", "callee": "get", "source_file": "C:\\TechVelora_nexalink\\src\\services\\realtimeService.jsx", "source_location": "L263"}, {"caller_nid": "realtimeservice_likepost", "callee": "exists", "source_file": "C:\\TechVelora_nexalink\\src\\services\\realtimeService.jsx", "source_location": "L264"}, {"caller_nid": "realtimeservice_likepost", "callee": "val", "source_file": "C:\\TechVelora_nexalink\\src\\services\\realtimeService.jsx", "source_location": "L265"}, {"caller_nid": "realtimeservice_likepost", "callee": "get", "source_file": "C:\\TechVelora_nexalink\\src\\services\\realtimeService.jsx", "source_location": "L267"}, {"caller_nid": "realtimeservice_likepost", "callee": "exists", "source_file": "C:\\TechVelora_nexalink\\src\\services\\realtimeService.jsx", "source_location": "L268"}, {"caller_nid": "realtimeservice_likepost", "callee": "remove", "source_file": "C:\\TechVelora_nexalink\\src\\services\\realtimeService.jsx", "source_location": "L269"}, {"caller_nid": "realtimeservice_likepost", "callee": "update", "source_file": "C:\\TechVelora_nexalink\\src\\services\\realtimeService.jsx", "source_location": "L270"}, {"caller_nid": "realtimeservice_likepost", "callee": "max", "source_file": "C:\\TechVelora_nexalink\\src\\services\\realtimeService.jsx", "source_location": "L270"}, {"caller_nid": "realtimeservice_likepost", "callee": "set", "source_file": "C:\\TechVelora_nexalink\\src\\services\\realtimeService.jsx", "source_location": "L273"}, {"caller_nid": "realtimeservice_likepost", "callee": "now", "source_file": "C:\\TechVelora_nexalink\\src\\services\\realtimeService.jsx", "source_location": "L273"}, {"caller_nid": "realtimeservice_likepost", "callee": "update", "source_file": "C:\\TechVelora_nexalink\\src\\services\\realtimeService.jsx", "source_location": "L274"}, {"caller_nid": "realtimeservice_addcomment", "callee": "ref", "source_file": "C:\\TechVelora_nexalink\\src\\services\\realtimeService.jsx", "source_location": "L281"}, {"caller_nid": "realtimeservice_addcomment", "callee": "push", "source_file": "C:\\TechVelora_nexalink\\src\\services\\realtimeService.jsx", "source_location": "L282"}, {"caller_nid": "realtimeservice_addcomment", "callee": "set", "source_file": "C:\\TechVelora_nexalink\\src\\services\\realtimeService.jsx", "source_location": "L283"}, {"caller_nid": "realtimeservice_addcomment", "callee": "now", "source_file": "C:\\TechVelora_nexalink\\src\\services\\realtimeService.jsx", "source_location": "L283"}, {"caller_nid": "realtimeservice_addcomment", "callee": "ref", "source_file": "C:\\TechVelora_nexalink\\src\\services\\realtimeService.jsx", "source_location": "L285"}, {"caller_nid": "realtimeservice_addcomment", "callee": "get", "source_file": "C:\\TechVelora_nexalink\\src\\services\\realtimeService.jsx", "source_location": "L286"}, {"caller_nid": "realtimeservice_addcomment", "callee": "exists", "source_file": "C:\\TechVelora_nexalink\\src\\services\\realtimeService.jsx", "source_location": "L287"}, {"caller_nid": "realtimeservice_addcomment", "callee": "update", "source_file": "C:\\TechVelora_nexalink\\src\\services\\realtimeService.jsx", "source_location": "L288"}, {"caller_nid": "realtimeservice_addcomment", "callee": "val", "source_file": "C:\\TechVelora_nexalink\\src\\services\\realtimeService.jsx", "source_location": "L288"}, {"caller_nid": "realtimeservice_getcomments", "callee": "get", "source_file": "C:\\TechVelora_nexalink\\src\\services\\realtimeService.jsx", "source_location": "L295"}, {"caller_nid": "realtimeservice_getcomments", "callee": "ref", "source_file": "C:\\TechVelora_nexalink\\src\\services\\realtimeService.jsx", "source_location": "L295"}, {"caller_nid": "realtimeservice_getcomments", "callee": "exists", "source_file": "C:\\TechVelora_nexalink\\src\\services\\realtimeService.jsx", "source_location": "L297"}, {"caller_nid": "realtimeservice_getcomments", "callee": "entries", "source_file": "C:\\TechVelora_nexalink\\src\\services\\realtimeService.jsx", "source_location": "L298"}, {"caller_nid": "realtimeservice_getcomments", "callee": "val", "source_file": "C:\\TechVelora_nexalink\\src\\services\\realtimeService.jsx", "source_location": "L298"}, {"caller_nid": "realtimeservice_getcomments", "callee": "push", "source_file": "C:\\TechVelora_nexalink\\src\\services\\realtimeService.jsx", "source_location": "L299"}, {"caller_nid": "realtimeservice_getcomments", "callee": "sort", "source_file": "C:\\TechVelora_nexalink\\src\\services\\realtimeService.jsx", "source_location": "L302"}]}